Workbook
Name aporte: [1]APP!$D$17
Name Aporte: Investimentos!$D$11
Name patrimonio: [1]APP!$D$20
Name Patrimonio: Investimentos!$D$14
Name Perfil: Perfil_Investimento!$G$3:$G$5
Name qtd_anos: [1]APP!$D$18
Name Qtde_Anos: Investimentos!$D$12
Name rendimento_carteira: [1]APP!$D$13
Name Rendimento_Carteira: Investimentos!$D$6
Name taxa_mensal: [1]APP!$D$19
Name Taxa_Mensal: Investimentos!$D$13

Sheet Investimentos
B4: CONFIGURAÇÕES
B5: Salário | D5: 2500
B6: Rendimento Carteira | D6: 0.006
B7: Percentual de Investimento | D7: 0.15
B8: Valor de Investimento | D8: =D5 * D7 -> 375
B10: INVESTIMENTO MENSAL
B11: Quanto investir por mês? | D11: =D8 -> 375
B12: Por Quantos Anos? | D12: 10
B13: Taxa de Rendimento mensal? | D13: 0.01079
B14: Patrimônio acumulado? | D14: =FV(Taxa_Mensal, Qtde_Anos * 12, Aporte * -1) -> 91231.58
B15: Dividendos Mensais? | D15: =Patrimonio * Rendimento_Carteira -> 547.38948
A17: 2 | B17: Cenários | D17: Dividendo
A18: 5 | B18: Quanto em 2 Anos? | C18: =FV(Taxa_Mensal, $A17 * 12, Aporte * -1) -> 10210.36 | D18: =$C18 * Rendimento_Carteira -> 61.262161
A19: 10 | B19: Quanto em 5 Anos? | C19: =FV(Taxa_Mensal, $A18 * 12, Aporte * -1) -> 31416.343 | D19: =$C19 * Rendimento_Carteira -> 188.49806
A20: 20 | B20: Quanto em 10 Anos? | C20: =FV(Taxa_Mensal, $A19 * 12, Aporte * -1) -> 91231.58 | D20: =$C20 * Rendimento_Carteira -> 547.38948
A21: 30 | B21: Quanto em 20 Anos? | C21: =FV(Taxa_Mensal, $A20 * 12, Aporte * -1) -> 421949.4 | D21: =$C21 * Rendimento_Carteira -> 2531.6964
B22: Quanto em 30 Anos? | C22: =FV(Taxa_Mensal, $A21 * 12, Aporte * -1) -> 1620813.6 | D22: =$C22 * Rendimento_Carteira -> 9724.8817
B25: PERFIL | D25: Moderado
B26: VALOR A SER INVESTIDO POR MÊS | D26: =Aporte -> 375
B28: TIPO DE FII | C28: Percentual Sugerido | D28: Valores
B29: PAPEL | C29: =VLOOKUP($D$25 & "-" & $B29, Perfil_Investimento!$B$2:$E$20, 4, FALSE) -> 0.32 | D29: =C29*$D$26 -> 120
B30: TIJOLO | C30: =VLOOKUP($D$25 & "-" & $B30, Perfil_Investimento!$B$2:$E$20, 4, FALSE) -> 0.35 | D30: =C30*$D$26 -> 131.25
B31: HÍBRIDOS | C31: =VLOOKUP($D$25 & "-" & $B31, Perfil_Investimento!$B$2:$E$20, 4, FALSE) -> 0.08 | D31: =C31*$D$26 -> 30
B32: FOFs | C32: =VLOOKUP($D$25 & "-" & $B32, Perfil_Investimento!$B$2:$E$20, 4, FALSE) -> 0.05 | D32: =C32*$D$26 -> 18.75
B33: DESENVOLVIMENTO | C33: =VLOOKUP($D$25 & "-" & $B33, Perfil_Investimento!$B$2:$E$20, 4, FALSE) -> 0.1 | D33: =C33*$D$26 -> 37.5
B34: HOTELARIAS | C34: =VLOOKUP($D$25 & "-" & $B34, Perfil_Investimento!$B$2:$E$20, 4, FALSE) -> 0.1 | D34: =C34*$D$26 -> 37.5
B35: Valor Total (R$) | D35: =SUM(D29:D34) -> 375

Sheet Perfil_Investimento
B2: CHAVE | C2: PERFIL | D2: TIPO DE FII | E2: % | G2: Perfil
B3: =C3&"-"&D3 -> Conservador-PAPEL | C3: Conservador | D3: PAPEL | E3: 0.3 | G3: {=_xlfn.UNIQUE(_xlfn._xlws.FILTER($C$3:$C$100, $C$3:$C$100 <>""))} -> Conservador | J3: %
B4: =C4&"-"&D4 -> Conservador-TIJOLO | C4: Conservador | D4: TIJOLO | E4: 0.5 | G4: Moderado | I4: Moderado-TIJOLO | J4: =VLOOKUP(I4, $B:$E, 4, FALSE) -> 0.35
B5: =C5&"-"&D5 -> Conservador-HÍBRIDOS | C5: Conservador | D5: HÍBRIDOS | E5: 0.1 | G5: Agressivo
B6: =C6&"-"&D6 -> Conservador-FOFs | C6: Conservador | D6: FOFs | E6: 0.1
B7: =C7&"-"&D7 -> Conservador-DESENVOLVIMENTO | C7: Conservador | D7: DESENVOLVIMENTO | E7: 0
B8: =C8&"-"&D8 -> Conservador-HOTELARIAS | C8: Conservador | D8: HOTELARIAS | E8: 0
B9: =C9&"-"&D9 -> Moderado-PAPEL | C9: Moderado | D9: PAPEL | E9: 0.32
B10: =C10&"-"&D10 -> Moderado-TIJOLO | C10: Moderado | D10: TIJOLO | E10: 0.35
B11: =C11&"-"&D11 -> Moderado-HÍBRIDOS | C11: Moderado | D11: HÍBRIDOS | E11: 0.08
B12: =C12&"-"&D12 -> Moderado-FOFs | C12: Moderado | D12: FOFs | E12: 0.05
B13: =C13&"-"&D13 -> Moderado-DESENVOLVIMENTO | C13: Moderado | D13: DESENVOLVIMENTO | E13: 0.1
B14: =C14&"-"&D14 -> Moderado-HOTELARIAS | C14: Moderado | D14: HOTELARIAS | E14: 0.1
B15: =C15&"-"&D15 -> Agressivo-PAPEL | C15: Agressivo | D15: PAPEL | E15: 0.5
B16: =C16&"-"&D16 -> Agressivo-TIJOLO | C16: Agressivo | D16: TIJOLO | E16: 0.1
B17: =C17&"-"&D17 -> Agressivo-HÍBRIDOS | C17: Agressivo | D17: HÍBRIDOS | E17: 0.05
... B20: =C20&"-"&D20 -> Agressivo-HOTELARIAS | C20: Agressivo | D20: HOTELARIAS | E20: 0.1
